brisque/__init__.py
brisque/brisque.py
brisque/models/__init__.py
brisque/models/normalize.pickle
brisque/models/svm.txt
brisque/tests/__init__.py
brisque/tests/test_brisque.py
brisque-0.0.17.dist-info/licenses/LICENSE
brisque-0.0.17.dist-info/METADATA
brisque-0.0.17.dist-info/WHEEL
brisque-0.0.17.dist-info/top_level.txt
brisque-0.0.17.dist-info/RECORD
