Metadata-Version: 2.4
Name: brisque
Version: 0.0.17
Summary: Image Quality
Home-page: https://github.com/rehanguha/brisque
Author: Rehan Guha
Author-email: rehanguha29@gmail.com
License: Apache-2.0
Keywords: quality,svm,image,maths
Classifier: Operating System :: OS Independent
Classifier: License :: OSI Approved :: MIT License
Classifier: Natural Language :: English
Classifier: Programming Language :: Python
Classifier: Topic :: Software Development :: Libraries :: Python Modules
Classifier: Topic :: Scientific/Engineering
Classifier: Intended Audience :: Developers
Requires-Python: >=2.7
License-File: LICENSE
Requires-Dist: numpy
Requires-Dist: scikit-image
Requires-Dist: scipy
Requires-Dist: opencv-python
Requires-Dist: libsvm-official
Requires-Dist: requests
Dynamic: author
Dynamic: author-email
Dynamic: classifier
Dynamic: description
Dynamic: description-content-type
Dynamic: home-page
Dynamic: keywords
Dynamic: license
Dynamic: license-file
Dynamic: requires-dist
Dynamic: requires-python
Dynamic: summary
